shpyx/__init__.py
shpyx/errors.py
shpyx/mypy.toml
shpyx/py.typed
shpyx/result.py
shpyx/runner.py
shpyx-0.0.34.dist-info/LICENSE
shpyx-0.0.34.dist-info/METADATA
shpyx-0.0.34.dist-info/WHEEL
shpyx-0.0.34.dist-info/entry_points.txt
shpyx-0.0.34.dist-info/RECORD
