Metadata-Version: 2.1
Name: shpyx
Version: 0.0.34
Summary: Run shell commands in Python
Home-page: https://github.com/Apakottur/shpyx
License: MIT
Keywords: shell,bash,terminal,script
Author: Yossi Rozantsev
Requires-Python: >=3.9,<4.0
Classifier: Development Status :: 5 - Production/Stable
Classifier: Intended Audience :: Developers
Classifier: License :: OSI Approved :: MIT License
Classifier: Operating System :: OS Independent
Classifier: Programming Language :: Python :: 3
Classifier: Programming Language :: Python :: 3.9
Classifier: Programming Language :: Python :: 3.10
Classifier: Programming Language :: Python :: 3.11
Classifier: Programming Language :: Python :: 3.12
Classifier: Topic :: Software Development :: Libraries
Classifier: Topic :: Software Development :: Libraries :: Python Modules
Project-URL: Documentation, https://github.com/Apakottur/shpyx
Project-URL: Repository, https://github.com/Apakottur/shpyx
